[
  {
    "D1C": "Ano (Código)",
    "D1N": "Ano",
    "D2C": "Variável (Código)",
    "D2N": "Variável",
    "D3C": "Município (Código)",
    "D3N": "Município",
    "MC": "Unidade de Medida (Código)",
    "MN": "Unidade de Medida",
    "V": "Valor"
  },
  {
    "D1C": "2010",
    "D1N": "2010",
    "D2C": "615",
    "D2N": "Área total das unidades territoriais",
    "D3C": "4200507",
    "D3N": "Águas de Chapecó - SC",
    "MC": "26",
    "MN": "Quilômetros quadrados",
    "V": "139.1"
  },
  {
    "D1C": "2010",
    "D1N": "2010",
    "D2C": "615",
    "D2N": "Área total das unidades territoriais",
    "D3C": "4200556",
    "D3N": "Águas Frias - SC",
    "MC": "26",
    "MN": "Quilômetros quadrados",
    "V": "75.2"
  },
  {
    "D1C": "2010",
    "D1N": "2010",
    "D2C": "615",
    "D2N": "Área total das unidades territoriais",
    "D3C": "4202578",
    "D3N": "Bom Jesus do Oeste - SC",
    "MC": "26",
    "MN": "Quilômetros quadrados",
    "V": "67.9"
  },
  {
    "D1C": "2010",
    "D1N": "2010",
    "D2C": "615",
    "D2N": "Área total das unidades territoriais",
    "D3C": "4203105",
    "D3N": "Caibi - SC",
    "MC": "26",
    "MN": "Quilômetros quadrados",
    "V": "171.7"
  },
  {
    "D1C": "2010",
    "D1N": "2010",
    "D2C": "615",
    "D2N": "Área total das unidades territoriais",
    "D3C": "4203501",
    "D3N": "Campo Erê - SC",
    "MC": "26",
    "MN": "Quilômetros quadrados",
    "V": "478.7"
  },
  {
    "D1C": "2010",
    "D1N": "2010",
    "D2C": "615",
    "D2N": "Área total das unidades territoriais",
    "D3C": "4204103",
    "D3N": "Caxambu do Sul - SC",
    "MC": "26",
    "MN": "Quilômetros quadrados",
    "V": "140.6"
  },
  {
    "D1C": "2010",
    "D1N": "2010",
    "D2C": "615",
    "D2N": "Área total das unidades territoriais",
    "D3C": "4204202",
    "D3N": "Chapecó - SC",
    "MC": "26",
    "MN": "Quilômetros quadrados",
    "V": "624.3"
  },
  {
    "D1C": "2010",
    "D1N": "2010",
    "D2C": "615",
    "D2N": "Área total das unidades territoriais",
    "D3C": "4204350",
    "D3N": "Cordilheira Alta - SC",
    "MC": "26",
    "MN": "Quilômetros quadrados",
    "V": "83.8"
  },
  {
    "D1C": "2010",
    "D1N": "2010",
    "D2C": "615",
    "D2N": "Área total das unidades territoriais",
    "D3C": "4204400",
    "D3N": "Coronel Freitas - SC",
    "MC": "26",
    "MN": "Quilômetros quadrados",
    "V": "234.2"
  },
  {
    "D1C": "2010",
    "D1N": "2010",
    "D2C": "615",
    "D2N": "Área total das unidades territoriais",
    "D3C": "4204707",
    "D3N": "Cunha Porã - SC",
    "MC": "26",
    "MN": "Quilômetros quadrados",
    "V": "220.3"
  },
  {
    "D1C": "2010",
    "D1N": "2010",
    "D2C": "615",
    "D2N": "Área total das unidades territoriais",
    "D3C": "4204756",
    "D3N": "Cunhataí - SC",
    "MC": "26",
    "MN": "Quilômetros quadrados",
    "V": "54.5"
  },
  {
    "D1C": "2010",
    "D1N": "2010",
    "D2C": "615",
    "D2N": "Área total das unidades territoriais",
    "D3C": "4205357",
    "D3N": "Flor do Sertão - SC",
    "MC": "26",
    "MN": "Quilômetros quadrados",
    "V": "58.7"
  },
  {
    "D1C": "2010",
    "D1N": "2010",
    "D2C": "615",
    "D2N": "Área total das unidades territoriais",
    "D3C": "4205431",
    "D3N": "Formosa do Sul - SC",
    "MC": "26",
    "MN": "Quilômetros quadrados",
    "V": "99.6"
  },
  {
    "D1C": "2010",
    "D1N": "2010",
    "D2C": "615",
    "D2N": "Área total das unidades territoriais",
    "D3C": "4206652",
    "D3N": "Guatambú - SC",
    "MC": "26",
    "MN": "Quilômetros quadrados",
    "V": "204.8"
  },
  {
    "D1C": "2010",
    "D1N": "2010",
    "D2C": "615",
    "D2N": "Área total das unidades territoriais",
    "D3C": "4207759",
    "D3N": "Iraceminha - SC",
    "MC": "26",
    "MN": "Quilômetros quadrados",
    "V": "164.4"
  },
  {
    "D1C": "2010",
    "D1N": "2010",
    "D2C": "615",
    "D2N": "Área total das unidades territoriais",
    "D3C": "4207858",
    "D3N": "Irati - SC",
    "MC": "26",
    "MN": "Quilômetros quadrados",
    "V": "77.5"
  },
  {
    "D1C": "2010",
    "D1N": "2010",
    "D2C": "615",
    "D2N": "Área total das unidades territoriais",
    "D3C": "4208955",
    "D3N": "Jardinópolis - SC",
    "MC": "26",
    "MN": "Quilômetros quadrados",
    "V": "68.1"
  },
  {
    "D1C": "2010",
    "D1N": "2010",
    "D2C": "615",
    "D2N": "Área total das unidades territoriais",
    "D3C": "4210506",
    "D3N": "Maravilha - SC",
    "MC": "26",
    "MN": "Quilômetros quadrados",
    "V": "169.4"
  },
  {
    "D1C": "2010",
    "D1N": "2010",
    "D2C": "615",
    "D2N": "Área total das unidades territoriais",
    "D3C": "4210902",
    "D3N": "Modelo - SC",
    "MC": "26",
    "MN": "Quilômetros quadrados",
    "V": "92.7"
  },
  {
    "D1C": "2010",
    "D1N": "2010",
    "D2C": "615",
    "D2N": "Área total das unidades territoriais",
    "D3C": "4211405",
    "D3N": "Nova Erechim - SC",
    "MC": "26",
    "MN": "Quilômetros quadrados",
    "V": "64.4"
  },
  {
    "D1C": "2010",
    "D1N": "2010",
    "D2C": "615",
    "D2N": "Área total das unidades territoriais",
    "D3C": "4211454",
    "D3N": "Nova Itaberaba - SC",
    "MC": "26",
    "MN": "Quilômetros quadrados",
    "V": "137.6"
  },
  {
    "D1C": "2010",
    "D1N": "2010",
    "D2C": "615",
    "D2N": "Área total das unidades territoriais",
    "D3C": "4211652",
    "D3N": "Novo Horizonte - SC",
    "MC": "26",
    "MN": "Quilômetros quadrados",
    "V": "151.7"
  },
  {
    "D1C": "2010",
    "D1N": "2010",
    "D2C": "615",
    "D2N": "Área total das unidades territoriais",
    "D3C": "4212106",
    "D3N": "Palmitos - SC",
    "MC": "26",
    "MN": "Quilômetros quadrados",
    "V": "350.7"
  },
  {
    "D1C": "2010",
    "D1N": "2010",
    "D2C": "615",
    "D2N": "Área total das unidades territoriais",
    "D3C": "4212908",
    "D3N": "Pinhalzinho - SC",
    "MC": "26",
    "MN": "Quilômetros quadrados",
    "V": "128.3"
  },
  {
    "D1C": "2010",
    "D1N": "2010",
    "D2C": "615",
    "D2N": "Área total das unidades territoriais",
    "D3C": "4213153",
    "D3N": "Planalto Alegre - SC",
    "MC": "26",
    "MN": "Quilômetros quadrados",
    "V": "62.6"
  },
  {
    "D1C": "2010",
    "D1N": "2010",
    "D2C": "615",
    "D2N": "Área total das unidades territoriais",
    "D3C": "4214201",
    "D3N": "Quilombo - SC",
    "MC": "26",
    "MN": "Quilômetros quadrados",
    "V": "279.3"
  },
  {
    "D1C": "2010",
    "D1N": "2010",
    "D2C": "615",
    "D2N": "Área total das unidades territoriais",
    "D3C": "4215356",
    "D3N": "Saltinho - SC",
    "MC": "26",
    "MN": "Quilômetros quadrados",
    "V": "156.5"
  },
  {
    "D1C": "2010",
    "D1N": "2010",
    "D2C": "615",
    "D2N": "Área total das unidades territoriais",
    "D3C": "4215687",
    "D3N": "Santa Terezinha do Progresso - SC",
    "MC": "26",
    "MN": "Quilômetros quadrados",
    "V": "119.0"
  },
  {
    "D1C": "2010",
    "D1N": "2010",
    "D2C": "615",
    "D2N": "Área total das unidades territoriais",
    "D3C": "4215695",
    "D3N": "Santiago do Sul - SC",
    "MC": "26",
    "MN": "Quilômetros quadrados",
    "V": "73.6"
  },
  {
    "D1C": "2010",
    "D1N": "2010",
    "D2C": "615",
    "D2N": "Área total das unidades territoriais",
    "D3C": "4215752",
    "D3N": "São Bernardino - SC",
    "MC": "26",
    "MN": "Quilômetros quadrados",
    "V": "145.0"
  },
  {
    "D1C": "2010",
    "D1N": "2010",
    "D2C": "615",
    "D2N": "Área total das unidades territoriais",
    "D3C": "4216008",
    "D3N": "São Carlos - SC",
    "MC": "26",
    "MN": "Quilômetros quadrados",
    "V": "159.0"
  },
  {
    "D1C": "2010",
    "D1N": "2010",
    "D2C": "615",
    "D2N": "Área total das unidades territoriais",
    "D3C": "4216909",
    "D3N": "São Lourenço do Oeste - SC",
    "MC": "26",
    "MN": "Quilômetros quadrados",
    "V": "361.8"
  },
  {
    "D1C": "2010",
    "D1N": "2010",
    "D2C": "615",
    "D2N": "Área total das unidades territoriais",
    "D3C": "4217154",
    "D3N": "São Miguel da Boa Vista - SC",
    "MC": "26",
    "MN": "Quilômetros quadrados",
    "V": "71.9"
  },
  {
    "D1C": "2010",
    "D1N": "2010",
    "D2C": "615",
    "D2N": "Área total das unidades territoriais",
    "D3C": "4217303",
    "D3N": "Saudades - SC",
    "MC": "26",
    "MN": "Quilômetros quadrados",
    "V": "205.6"
  },
  {
    "D1C": "2010",
    "D1N": "2010",
    "D2C": "615",
    "D2N": "Área total das unidades territoriais",
    "D3C": "4217550",
    "D3N": "Serra Alta - SC",
    "MC": "26",
    "MN": "Quilômetros quadrados",
    "V": "90.4"
  },
  {
    "D1C": "2010",
    "D1N": "2010",
    "D2C": "615",
    "D2N": "Área total das unidades territoriais",
    "D3C": "4217758",
    "D3N": "Sul Brasil - SC",
    "MC": "26",
    "MN": "Quilômetros quadrados",
    "V": "112.7"
  },
  {
    "D1C": "2010",
    "D1N": "2010",
    "D2C": "615",
    "D2N": "Área total das unidades territoriais",
    "D3C": "4217956",
    "D3N": "Tigrinhos - SC",
    "MC": "26",
    "MN": "Quilômetros quadrados",
    "V": "57.4"
  },
  {
    "D1C": "2010",
    "D1N": "2010",
    "D2C": "615",
    "D2N": "Área total das unidades territoriais",
    "D3C": "4218855",
    "D3N": "União do Oeste - SC",
    "MC": "26",
    "MN": "Quilômetros quadrados",
    "V": "93.1"
  }
]