[
  {
    "D1C": "Ano (Código)",
    "D1N": "Ano",
    "D2C": "Variável (Código)",
    "D2N": "Variável",
    "D3C": "Município (Código)",
    "D3N": "Município",
    "MC": "Unidade de Medida (Código)",
    "MN": "Unidade de Medida",
    "V": "Valor"
  },
  {
    "D1C": "2010",
    "D1N": "2010",
    "D2C": "615",
    "D2N": "Área total das unidades territoriais",
    "D3C": "2900603",
    "D3N": "Aiquara - BA",
    "MC": "26",
    "MN": "Quilômetros quadrados",
    "V": "159.7"
  },
  {
    "D1C": "2010",
    "D1N": "2010",
    "D2C": "615",
    "D2N": "Área total das unidades territoriais",
    "D3C": "2901007",
    "D3N": "Amargosa - BA",
    "MC": "26",
    "MN": "Quilômetros quadrados",
    "V": "463.2"
  },
  {
    "D1C": "2010",
    "D1N": "2010",
    "D2C": "615",
    "D2N": "Área total das unidades territoriais",
    "D3C": "2901957",
    "D3N": "Apuarema - BA",
    "MC": "26",
    "MN": "Quilômetros quadrados",
    "V": "154.9"
  },
  {
    "D1C": "2010",
    "D1N": "2010",
    "D2C": "615",
    "D2N": "Área total das unidades territoriais",
    "D3C": "2904308",
    "D3N": "Brejões - BA",
    "MC": "26",
    "MN": "Quilômetros quadrados",
    "V": "480.8"
  },
  {
    "D1C": "2010",
    "D1N": "2010",
    "D2C": "615",
    "D2N": "Área total das unidades territoriais",
    "D3C": "2909505",
    "D3N": "Cravolândia - BA",
    "MC": "26",
    "MN": "Quilômetros quadrados",
    "V": "162.2"
  },
  {
    "D1C": "2010",
    "D1N": "2010",
    "D2C": "615",
    "D2N": "Área total das unidades territoriais",
    "D3C": "2914208",
    "D3N": "Irajuba - BA",
    "MC": "26",
    "MN": "Quilômetros quadrados",
    "V": "413.5"
  },
  {
    "D1C": "2010",
    "D1N": "2010",
    "D2C": "615",
    "D2N": "Área total das unidades territoriais",
    "D3C": "2914307",
    "D3N": "Iramaia - BA",
    "MC": "26",
    "MN": "Quilômetros quadrados",
    "V": "1947.3"
  },
  {
    "D1C": "2010",
    "D1N": "2010",
    "D2C": "615",
    "D2N": "Área total das unidades territoriais",
    "D3C": "2915106",
    "D3N": "Itagi - BA",
    "MC": "26",
    "MN": "Quilômetros quadrados",
    "V": "259.2"
  },
  {
    "D1C": "2010",
    "D1N": "2010",
    "D2C": "615",
    "D2N": "Área total das unidades territoriais",
    "D3C": "2916708",
    "D3N": "Itaquara - BA",
    "MC": "26",
    "MN": "Quilômetros quadrados",
    "V": "323.0"
  },
  {
    "D1C": "2010",
    "D1N": "2010",
    "D2C": "615",
    "D2N": "Área total das unidades territoriais",
    "D3C": "2916906",
    "D3N": "Itiruçu - BA",
    "MC": "26",
    "MN": "Quilômetros quadrados",
    "V": "313.7"
  },
  {
    "D1C": "2010",
    "D1N": "2010",
    "D2C": "615",
    "D2N": "Área total das unidades territoriais",
    "D3C": "2917607",
    "D3N": "Jaguaquara - BA",
    "MC": "26",
    "MN": "Quilômetros quadrados",
    "V": "928.2"
  },
  {
    "D1C": "2010",
    "D1N": "2010",
    "D2C": "615",
    "D2N": "Área total das unidades territoriais",
    "D3C": "2918001",
    "D3N": "Jequié - BA",
    "MC": "26",
    "MN": "Quilômetros quadrados",
    "V": "3227.3"
  },
  {
    "D1C": "2010",
    "D1N": "2010",
    "D2C": "615",
    "D2N": "Área total das unidades territoriais",
    "D3C": "2918209",
    "D3N": "Jiquiriçá - BA",
    "MC": "26",
    "MN": "Quilômetros quadrados",
    "V": "239.4"
  },
  {
    "D1C": "2010",
    "D1N": "2010",
    "D2C": "615",
    "D2N": "Área total das unidades territoriais",
    "D3C": "2918308",
    "D3N": "Jitaúna - BA",
    "MC": "26",
    "MN": "Quilômetros quadrados",
    "V": "218.9"
  },
  {
    "D1C": "2010",
    "D1N": "2010",
    "D2C": "615",
    "D2N": "Área total das unidades territoriais",
    "D3C": "2918704",
    "D3N": "Lafaiete Coutinho - BA",
    "MC": "26",
    "MN": "Quilômetros quadrados",
    "V": "405.3"
  },
  {
    "D1C": "2010",
    "D1N": "2010",
    "D2C": "615",
    "D2N": "Área total das unidades territoriais",
    "D3C": "2918803",
    "D3N": "Laje - BA",
    "MC": "26",
    "MN": "Quilômetros quadrados",
    "V": "457.7"
  },
  {
    "D1C": "2010",
    "D1N": "2010",
    "D2C": "615",
    "D2N": "Área total das unidades territoriais",
    "D3C": "2919058",
    "D3N": "Lajedo do Tabocal - BA",
    "MC": "26",
    "MN": "Quilômetros quadrados",
    "V": "431.9"
  },
  {
    "D1C": "2010",
    "D1N": "2010",
    "D2C": "615",
    "D2N": "Área total das unidades territoriais",
    "D3C": "2920502",
    "D3N": "Maracás - BA",
    "MC": "26",
    "MN": "Quilômetros quadrados",
    "V": "2253.2"
  },
  {
    "D1C": "2010",
    "D1N": "2010",
    "D2C": "615",
    "D2N": "Área total das unidades territoriais",
    "D3C": "2920809",
    "D3N": "Marcionílio Souza - BA",
    "MC": "26",
    "MN": "Quilômetros quadrados",
    "V": "1277.2"
  },
  {
    "D1C": "2010",
    "D1N": "2010",
    "D2C": "615",
    "D2N": "Área total das unidades territoriais",
    "D3C": "2921302",
    "D3N": "Milagres - BA",
    "MC": "26",
    "MN": "Quilômetros quadrados",
    "V": "284.4"
  },
  {
    "D1C": "2010",
    "D1N": "2010",
    "D2C": "615",
    "D2N": "Área total das unidades territoriais",
    "D3C": "2922409",
    "D3N": "Mutuípe - BA",
    "MC": "26",
    "MN": "Quilômetros quadrados",
    "V": "283.2"
  },
  {
    "D1C": "2010",
    "D1N": "2010",
    "D2C": "615",
    "D2N": "Área total das unidades territoriais",
    "D3C": "2922805",
    "D3N": "Nova Itarana - BA",
    "MC": "26",
    "MN": "Quilômetros quadrados",
    "V": "470.4"
  },
  {
    "D1C": "2010",
    "D1N": "2010",
    "D2C": "615",
    "D2N": "Área total das unidades territoriais",
    "D3C": "2924900",
    "D3N": "Planaltino - BA",
    "MC": "26",
    "MN": "Quilômetros quadrados",
    "V": "927.0"
  },
  {
    "D1C": "2010",
    "D1N": "2010",
    "D2C": "615",
    "D2N": "Área total das unidades territoriais",
    "D3C": "2927903",
    "D3N": "Santa Inês - BA",
    "MC": "26",
    "MN": "Quilômetros quadrados",
    "V": "315.7"
  },
  {
    "D1C": "2010",
    "D1N": "2010",
    "D2C": "615",
    "D2N": "Área total das unidades territoriais",
    "D3C": "2929404",
    "D3N": "São Miguel das Matas - BA",
    "MC": "26",
    "MN": "Quilômetros quadrados",
    "V": "214.4"
  },
  {
    "D1C": "2010",
    "D1N": "2010",
    "D2C": "615",
    "D2N": "Área total das unidades territoriais",
    "D3C": "2932101",
    "D3N": "Ubaíra - BA",
    "MC": "26",
    "MN": "Quilômetros quadrados",
    "V": "726.3"
  }
]