[
  {
    "D1C": "Ano (Código)",
    "D1N": "Ano",
    "D2C": "Variável (Código)",
    "D2N": "Variável",
    "D3C": "Município (Código)",
    "D3N": "Município",
    "MC": "Unidade de Medida (Código)",
    "MN": "Unidade de Medida",
    "V": "Valor"
  },
  {
    "D1C": "2010",
    "D1N": "2010",
    "D2C": "615",
    "D2N": "Área total das unidades territoriais",
    "D3C": "3300209",
    "D3N": "Araruama - RJ",
    "MC": "26",
    "MN": "Quilômetros quadrados",
    "V": "638.0"
  },
  {
    "D1C": "2010",
    "D1N": "2010",
    "D2C": "615",
    "D2N": "Área total das unidades territoriais",
    "D3C": "3300233",
    "D3N": "Armação dos Búzios - RJ",
    "MC": "26",
    "MN": "Quilômetros quadrados",
    "V": "70.3"
  },
  {
    "D1C": "2010",
    "D1N": "2010",
    "D2C": "615",
    "D2N": "Área total das unidades territoriais",
    "D3C": "3300258",
    "D3N": "Arraial do Cabo - RJ",
    "MC": "26",
    "MN": "Quilômetros quadrados",
    "V": "160.3"
  },
  {
    "D1C": "2010",
    "D1N": "2010",
    "D2C": "615",
    "D2N": "Área total das unidades territoriais",
    "D3C": "3300704",
    "D3N": "Cabo Frio - RJ",
    "MC": "26",
    "MN": "Quilômetros quadrados",
    "V": "410.4"
  },
  {
    "D1C": "2010",
    "D1N": "2010",
    "D2C": "615",
    "D2N": "Área total das unidades territoriais",
    "D3C": "3301876",
    "D3N": "Iguaba Grande - RJ",
    "MC": "26",
    "MN": "Quilômetros quadrados",
    "V": "51.9"
  },
  {
    "D1C": "2010",
    "D1N": "2010",
    "D2C": "615",
    "D2N": "Área total das unidades territoriais",
    "D3C": "3305208",
    "D3N": "São Pedro da Aldeia - RJ",
    "MC": "26",
    "MN": "Quilômetros quadrados",
    "V": "332.8"
  },
  {
    "D1C": "2010",
    "D1N": "2010",
    "D2C": "615",
    "D2N": "Área total das unidades territoriais",
    "D3C": "3305505",
    "D3N": "Saquarema - RJ",
    "MC": "26",
    "MN": "Quilômetros quadrados",
    "V": "353.6"
  }
]